localrag/__init__.py
localrag/chatresponse.py
localrag/ragchat.py
localrag/utils.py
localrag-0.1.52.dist-info/LICENSE
localrag-0.1.52.dist-info/METADATA
localrag-0.1.52.dist-info/WHEEL
localrag-0.1.52.dist-info/top_level.txt
localrag-0.1.52.dist-info/RECORD
