Metadata-Version: 2.1
Name: localrag
Version: 0.1.52
Summary: Chat with your documents locally.
Home-page: https://github.com/banjtheman/localrag
Author: Banjo Obayomi
Author-email: banjtheman@gmail.com
License-File: LICENSE
Requires-Dist: unstructured
Requires-Dist: unstructured[all-docs]
Requires-Dist: langchain
Requires-Dist: langchain-community
Requires-Dist: langchain-core
Requires-Dist: faiss-cpu
Requires-Dist: transformers
Requires-Dist: sentence-transformers
